pennylane_qrack/CMakeCache.txt
pennylane_qrack/Makefile
pennylane_qrack/QrackAceDeviceConfig.toml
pennylane_qrack/QrackDeviceConfig.toml
pennylane_qrack/QrackStabilizerDeviceConfig.toml
pennylane_qrack/__init__.py
pennylane_qrack/_version.py
pennylane_qrack/cmake_install.cmake
pennylane_qrack/libqrack_device.dylib
pennylane_qrack/qrack_ace_device.py
pennylane_qrack/qrack_device.cpp
pennylane_qrack/qrack_device.py
pennylane_qrack/qrack_stabilizer_device.py
pennylane_qrack-0.26.0.dist-info/licenses/LICENSE
pennylane_qrack-0.26.0.dist-info/METADATA
pennylane_qrack-0.26.0.dist-info/WHEEL
pennylane_qrack-0.26.0.dist-info/entry_points.txt
pennylane_qrack-0.26.0.dist-info/top_level.txt
pennylane_qrack-0.26.0.dist-info/RECORD
